COOLBOOY/__init__.py
COOLBOOY/__main__.py
COOLBOOY/init.py
COOLBOOY/assets/code.jpg
COOLBOOY/assets/help.jpg
COOLBOOY/assets/logo.png
COOLBOOY/assets/pkginstall.jpg
COOLBOOY/cli/__init__.py
COOLBOOY/cli/commands.py
COOLBOOY/cli/editor.py
COOLBOOY/cli/interface.py
COOLBOOY/cli/main.py
COOLBOOY/cli/parser.py
COOLBOOY/cli/query_handler.py
COOLBOOY/core/__init__.py
COOLBOOY/core/ai_interface.py
COOLBOOY/core/config.py
COOLBOOY/core/manager.py
COOLBOOY/core/updater.py
COOLBOOY/modes/__init__.py
COOLBOOY/modes/base.py
COOLBOOY/modes/chat.py
COOLBOOY/modes/code.py
COOLBOOY/modes/shell.py
COOLBOOY/modes/standard.py
COOLBOOY/utils/__init__.py
COOLBOOY/utils/console.py
COOLBOOY/utils/file_handler.py
COOLBOOY/utils/validation.py
coolbooy-1.2.1.dist-info/licenses/LICENSE
coolbooy-1.2.1.dist-info/METADATA
coolbooy-1.2.1.dist-info/WHEEL
coolbooy-1.2.1.dist-info/entry_points.txt
coolbooy-1.2.1.dist-info/top_level.txt
coolbooy-1.2.1.dist-info/RECORD
