Metadata-Version: 2.4
Name: COOLBOOY
Version: 1.2.1
Summary: COOLBOOY-Multi-Provider AI Assistant for developers and power users
Author: coolbooy
Author-email: 𝐈𝐌 𝐂𝐎𝐎𝐋 𝐁𝐎𝐎𝐘 𝓢𝓱𝓪𝓭𝓸𝔀 𝓚𝓲𝓷𝓰 <coolbooy@gmail.com>
License-Expression: MIT
Keywords: COOLBOOY-Multi-Provider AI Assistant
Classifier: Programming Language :: Python :: 3
Classifier: Operating System :: OS Independent
Classifier: Intended Audience :: Developers
Requires-Python: >=3.6
License-File: LICENSE
Dynamic: author
Dynamic: license-file
Dynamic: requires-python
